py_cmdoptions/__init__.py
py_cmdoptions/executor.py
py_cmdoptions/option.py
py_cmdoptions/examples/python.py
py_cmdoptions-0.0.2.dist-info/licenses/LICENSE
py_cmdoptions-0.0.2.dist-info/METADATA
py_cmdoptions-0.0.2.dist-info/WHEEL
py_cmdoptions-0.0.2.dist-info/top_level.txt
py_cmdoptions-0.0.2.dist-info/RECORD
