Metadata-Version: 2.4
Name: py_cmdoptions
Version: 0.0.2
Summary: To create command-line and options.
Author-email: ThankVinci <thankvinci@163.com>
Project-URL: Homepage, https://github.com/ThankVinci/py-cmdoptions
Project-URL: Repository, https://github.com/ThankVinci/py-cmdoptions.git
Keywords: command-line,options
Requires-Python: >=3.8
License-File: LICENSE
Provides-Extra: dev
Dynamic: license-file
